robocorp/browser/__init__.py
robocorp/browser/__main__.py
robocorp/browser/_config.py
robocorp/browser/_context.py
robocorp/browser/_engines.py
robocorp/browser/_types.py
robocorp/browser/cli.py
robocorp/browser/py.typed
robocorp_browser-2.3.4.dist-info/METADATA
robocorp_browser-2.3.4.dist-info/WHEEL
robocorp_browser-2.3.4.dist-info/RECORD
