Metadata-Version: 2.1
Name: robocorp-browser
Version: 2.3.4
Summary: Robocorp browser automation library
Home-page: https://github.com/robocorp/robocorp/
License: Apache-2.0
Author: Fabio Z.
Author-email: fabio@robocorp.com
Requires-Python: >=3.9,<4.0
Classifier: License :: OSI Approved :: Apache Software License
Classifier: Programming Language :: Python :: 3
Classifier: Programming Language :: Python :: 3.9
Classifier: Programming Language :: Python :: 3.10
Classifier: Programming Language :: Python :: 3.11
Classifier: Programming Language :: Python :: 3.12
Requires-Dist: playwright (>=1.32.1,<2.0.0)
Requires-Dist: robocorp-tasks (>=1,<4)
Project-URL: Repository, https://github.com/robocorp/robocorp/
